LICENSE
MANIFEST.in
README.md
notehub.py
setup.py
notehub.egg-info/PKG-INFO
notehub.egg-info/SOURCES.txt
notehub.egg-info/dependency_links.txt
notehub.egg-info/requires.txt
notehub.egg-info/top_level.txt