Metadata-Version: 1.0
Name: notehub
Version: 0.4
Summary: A simple wrapper for the Notehub.org API.
Home-page: https://github.com/seanwatson/notehub
Author: Sean Watson
Author-email: UNKNOWN
License: MIT
Keywords: notehub
Platform: UNKNOWN
